{
  "meta": {
    "symbol": "AAPL",
    "interval": "1day",
    "currency": "USD",
    "exchange_timezone": "America/New_York",
    "exchange": "NASDAQ",
    "mic_code": "XNGS",
    "type": "Common Stock",
    "indicator": {
      "name": "SMA - Simple Moving Average",
      "series_type": "close",
      "time_period": 12
    }
  },
  "values": [
    {
      "datetime": "2025-08-22",
      "sma": "228.66916"
    },
    {
      "datetime": "2025-08-21",
      "sma": "227.46000"
    },
    {
      "datetime": "2025-08-20",
      "sma": "225.62833"
    },
    {
      "datetime": "2025-08-19",
      "sma": "223.74000"
    },
    {
      "datetime": "2025-08-18",
      "sma": "221.39167"
    },
    {
      "datetime": "2025-08-15",
      "sma": "219.44833"
    },
    {
      "datetime": "2025-08-14",
      "sma": "217.57000"
    },
    {
      "datetime": "2025-08-13",
      "sma": "215.77750"
    },
    {
      "datetime": "2025-08-12",
      "sma": "214.17083"
    },
    {
      "datetime": "2025-08-11",
      "sma": "212.85667"
    },
    {
      "datetime": "2025-08-08",
      "sma": "211.73834"
    },
    {
      "datetime": "2025-08-07",
      "sma": "210.47167"
    },
    {
      "datetime": "2025-08-06",
      "sma": "210.0025012"
    },
    {
      "datetime": "2025-08-05",
      "sma": "209.93833"
    },
    {
      "datetime": "2025-08-04",
      "sma": "210.62667"
    },
    {
      "datetime": "2025-08-01",
      "sma": "211.18250"
    },
    {
      "datetime": "2025-07-31",
      "sma": "211.83083"
    },
    {
      "datetime": "2025-07-30",
      "sma": "211.95917"
    },
    {
      "datetime": "2025-07-29",
      "sma": "211.92333"
    },
    {
      "datetime": "2025-07-28",
      "sma": "211.91417"
    },
    {
      "datetime": "2025-07-25",
      "sma": "211.77750"
    },
    {
      "datetime": "2025-07-24",
      "sma": "211.54917"
    },
    {
      "datetime": "2025-07-23",
      "sma": "211.23667"
    },
    {
      "datetime": "2025-07-22",
      "sma": "210.88667"
    },
    {
      "datetime": "2025-07-21",
      "sma": "210.81583"
    },
    {
      "datetime": "2025-07-18",
      "sma": "210.81250"
    },
    {
      "datetime": "2025-07-17",
      "sma": "210.53250"
    },
    {
      "datetime": "2025-07-16",
      "sma": "210.12833"
    },
    {
      "datetime": "2025-07-15",
      "sma": "209.37167"
    },
    {
      "datetime": "2025-07-14",
      "sma": "208.69583"
    }
  ],
  "status": "ok"
}