{
  "news": [
    {
      "author": "Surbhi Jain",
      "content": "",
      "created_at": "2025-08-28T19:31:25Z",
      "headline": "Apple, Google, Nvidia Unleash $430 Billion Buyback Blitz—But Is Innovation Falling Behind?",
      "id": 47398153,
      "images": [
        {
          "size": "large",
          "url": "https://cdn.benzinga.com/files/imagecache/2048x1536xUP/images/story/2025/08/28/Concept-Of-Share-Buyback-Write-On-Sticky.jpeg"
        },
        {
          "size": "small",
          "url": "https://cdn.benzinga.com/files/imagecache/1024x768xUP/images/story/2025/08/28/Concept-Of-Share-Buyback-Write-On-Sticky.jpeg"
        },
        {
          "size": "thumb",
          "url": "https://cdn.benzinga.com/files/imagecache/250x187xUP/images/story/2025/08/28/Concept-Of-Share-Buyback-Write-On-Sticky.jpeg"
        }
      ],
      "source": "benzinga",
      "summary": "Apple, Alphabet, and Nvidia are flexing their financial power with $430 billion in stock buybacks. Skeptics question their motives.",
      "symbols": [
        "AAPL",
        "BAC",
        "GOOG",
        "GOOGL",
        "GS",
        "JPM",
        "NVDA",
        "V",
        "WFC"
      ],
      "updated_at": "2025-08-28T19:31:25Z",
      "url": "https://www.benzinga.com/markets/tech/25/08/47398153/apple-google-nvidia-unleash-430-billion-buyback-blitz-but-is-innovation-falling-behind"
    },
    {
      "author": "Surbhi Jain",
      "content": "",
      "created_at": "2025-08-28T17:55:40Z",
      "headline": "Apple–TSMC Chip Pact Builds Firewall Against Trump's Tariffs",
      "id": 47395492,
      "images": [
        {
          "size": "large",
          "url": "https://cdn.benzinga.com/files/imagecache/2048x1536xUP/images/story/2025/08/28/Pune--India---February-19--2024--Apple-i_0.jpeg"
        },
        {
          "size": "small",
          "url": "https://cdn.benzinga.com/files/imagecache/1024x768xUP/images/story/2025/08/28/Pune--India---February-19--2024--Apple-i_0.jpeg"
        },
        {
          "size": "thumb",
          "url": "https://cdn.benzinga.com/files/imagecache/250x187xUP/images/story/2025/08/28/Pune--India---February-19--2024--Apple-i_0.jpeg"
        }
      ],
      "source": "benzinga",
      "summary": " Apple building a moat, securing supply and erecting a firewall against Trump&#39;s tariffs. First-mover advantage in chips and U.S investments shield them from rivals and political storms.",
      "symbols": [
        "AAPL",
        "AMD",
        "GOOG",
        "GOOGL",
        "NVDA",
        "QCOM",
        "SSNLF",
        "TSM"
      ],
      "updated_at": "2025-08-28T17:55:41Z",
      "url": "https://www.benzinga.com/markets/tech/25/08/47395492/apple-tsmc-chip-pact-builds-firewall-against-trumps-tariffs"
    },
    {
      "author": "Anusuya Lahiri",
      "content": "",
      "created_at": "2025-08-28T17:14:39Z",
      "headline": "What's Going On With Marvell Technology Stock Thursday?",
      "id": 47394308,
      "images": [
        {
          "size": "large",
          "url": "https://cdn.benzinga.com/files/imagecache/2048x1536xUP/images/story/2025/08/28/Marvell-Technology_0.jpeg"
        },
        {
          "size": "small",
          "url": "https://cdn.benzinga.com/files/imagecache/1024x768xUP/images/story/2025/08/28/Marvell-Technology_0.jpeg"
        },
        {
          "size": "thumb",
          "url": "https://cdn.benzinga.com/files/imagecache/250x187xUP/images/story/2025/08/28/Marvell-Technology_0.jpeg"
        }
      ],
      "source": "benzinga",
      "summary": "Marvell (MRVL) shares surged on expectations of strong Q2 results, driven by increasing demand for AI infrastructure and competition with Nvidia.",
      "symbols": [
        "AAPL",
        "AMZN",
        "META",
        "MRVL",
        "MSFT",
        "NVDA"
      ],
      "updated_at": "2025-08-28T17:18:20Z",
      "url": "https://www.benzinga.com/markets/tech/25/08/47394308/whats-going-on-with-marvell-technology-stock-thursday"
    },
    {
      "author": "Benzinga Insights",
      "content": "",
      "created_at": "2025-08-28T15:01:01Z",
      "headline": "Exploring The Competitive Space: Apple Versus Industry Peers In Technology Hardware, Storage &amp; Peripherals",
      "id": 47389570,
      "images": [],
      "source": "benzinga",
      "summary": " ",
      "symbols": [
        "AAPL"
      ],
      "updated_at": "2025-08-28T15:01:01Z",
      "url": "https://www.benzinga.com/insights/news/25/08/47389570/exploring-the-competitive-space-apple-versus-industry-peers-in-technology-hardware-storage-amp-peri"
    },
    {
      "author": "Anusuya Lahiri",
      "content": "",
      "created_at": "2025-08-28T14:37:15Z",
      "headline": "Broadcom Stock Jumps After Nvidia Forecasts Massive AI Demand",
      "id": 47388461,
      "images": [
        {
          "size": "large",
          "url": "https://cdn.benzinga.com/files/imagecache/2048x1536xUP/images/story/2025/08/28/Broadcom.jpeg"
        },
        {
          "size": "small",
          "url": "https://cdn.benzinga.com/files/imagecache/1024x768xUP/images/story/2025/08/28/Broadcom.jpeg"
        },
        {
          "size": "thumb",
          "url": "https://cdn.benzinga.com/files/imagecache/250x187xUP/images/story/2025/08/28/Broadcom.jpeg"
        }
      ],
      "source": "benzinga",
      "summary": "Broadcom (AVGO) shares rose after Nvidia (NVDA) reported strong earnings, reassuring investors of continued demand for AI chips.",
      "symbols": [
        "AAPL",
        "AVGO",
        "META",
        "MSFT",
        "NVDA"
      ],
      "updated_at": "2025-08-28T14:38:48Z",
      "url": "https://www.benzinga.com/markets/tech/25/08/47388461/broadcom-stock-jumps-after-nvidia-forecasts-massive-ai-demand"
    },
    {
      "author": "Avi Kapoor",
      "content": "",
      "created_at": "2025-08-28T12:32:40Z",
      "headline": "Apple, FTAI Aviation, Coeur Mining And An Energy Stock: CNBC's 'Final Trades'",
      "id": 47383568,
      "images": [
        {
          "size": "large",
          "url": "https://cdn.benzinga.com/files/imagecache/2048x1536xUP/images/story/2025/08/28/Serious-Business-Man-Trader-Analyst-Look.jpeg"
        },
        {
          "size": "small",
          "url": "https://cdn.benzinga.com/files/imagecache/1024x768xUP/images/story/2025/08/28/Serious-Business-Man-Trader-Analyst-Look.jpeg"
        },
        {
          "size": "thumb",
          "url": "https://cdn.benzinga.com/files/imagecache/250x187xUP/images/story/2025/08/28/Serious-Business-Man-Trader-Analyst-Look.jpeg"
        }
      ],
      "source": "benzinga",
      "summary": "Summary: Investors face complex market with tech and commodities driving different stories. Analysts bullish on FTAI, AAPL, CDE, PSX. See premarket coverage.",
      "symbols": [
        "AAPL",
        "CDE",
        "FTAI",
        "NVDA",
        "PSX"
      ],
      "updated_at": "2025-08-28T12:32:41Z",
      "url": "https://www.benzinga.com/trading-ideas/long-ideas/25/08/47383568/apple-ftai-aviation-coeur-mining-and-an-energy-stock-cnbcs-final-trades"
    },
    {
      "author": "Namrata Sen",
      "content": "",
      "created_at": "2025-08-28T11:19:39Z",
      "headline": "Apple Stock Could Hit An 'All-Time High' The Day It Does This, Says Analyst",
      "id": 47380701,
      "images": [
        {
          "size": "large",
          "url": "https://cdn.benzinga.com/files/imagecache/2048x1536xUP/images/story/2025/08/28/Pune--India---February-19--2024--Apple-i.jpeg"
        },
        {
          "size": "small",
          "url": "https://cdn.benzinga.com/files/imagecache/1024x768xUP/images/story/2025/08/28/Pune--India---February-19--2024--Apple-i.jpeg"
        },
        {
          "size": "thumb",
          "url": "https://cdn.benzinga.com/files/imagecache/250x187xUP/images/story/2025/08/28/Pune--India---February-19--2024--Apple-i.jpeg"
        }
      ],
      "source": "benzinga",
      "summary": "Josh Brown, CEO of Ritholtz Wealth Management, has projected that the shares of Apple Inc. (NASDAQ: AAPL) could hit an all-time high if the tech behemoth goes ahead with its plans to acquire Perplexity AI.",
      "symbols": [
        "AAPL",
        "GOOG",
        "GOOGL",
        "MSFT",
        "T"
      ],
      "updated_at": "2025-08-28T11:19:40Z",
      "url": "https://www.benzinga.com/markets/tech/25/08/47380701/apple-stock-could-hit-an-all-time-high-the-day-it-does-this-says-analyst"
    },
    {
      "author": "Namrata Sen",
      "content": "",
      "created_at": "2025-08-28T08:12:02Z",
      "headline": "Apple Takes On Spotify, Expands Music Service To TuneIn's 75 Million Users: Report",
      "id": 47377888,
      "images": [
        {
          "size": "large",
          "url": "https://cdn.benzinga.com/files/imagecache/2048x1536xUP/images/story/2025/08/28/Munich--Germany---10--March-2023-Apple-M.jpeg"
        },
        {
          "size": "small",
          "url": "https://cdn.benzinga.com/files/imagecache/1024x768xUP/images/story/2025/08/28/Munich--Germany---10--March-2023-Apple-M.jpeg"
        },
        {
          "size": "thumb",
          "url": "https://cdn.benzinga.com/files/imagecache/250x187xUP/images/story/2025/08/28/Munich--Germany---10--March-2023-Apple-M.jpeg"
        }
      ],
      "source": "benzinga",
      "summary": "Apple Inc. (NASDAQ: AAPL) reportedly plans to expand its music service by making its curated radio stations available worldwide through home speakers and connected cars.",
      "symbols": [
        "AAPL",
        "SPOT"
      ],
      "updated_at": "2025-08-28T08:12:03Z",
      "url": "https://www.benzinga.com/news/entertainment/25/08/47377888/apple-takes-on-spotify-expands-music-service-to-tuneins-75-million-users-report"
    },
    {
      "author": "Benzinga Insights",
      "content": "",
      "created_at": "2025-08-27T19:02:30Z",
      "headline": "Smart Money Is Betting Big In AAPL Options",
      "id": 47368340,
      "images": [],
      "source": "benzinga",
      "summary": " ",
      "symbols": [
        "AAPL"
      ],
      "updated_at": "2025-08-27T19:02:31Z",
      "url": "https://www.benzinga.com/insights/options/25/08/47368340/smart-money-is-betting-big-in-aapl-options"
    },
    {
      "author": "Surbhi Jain",
      "content": "",
      "created_at": "2025-08-27T16:59:49Z",
      "headline": "Apple Hunts Big AI Deals — But Time Warner, Nokia Still Haunt The M&A Playbook",
      "id": 47365037,
      "images": [
        {
          "size": "large",
          "url": "https://cdn.benzinga.com/files/imagecache/2048x1536xUP/images/story/2025/08/27/Apple-Store.jpeg"
        },
        {
          "size": "small",
          "url": "https://cdn.benzinga.com/files/imagecache/1024x768xUP/images/story/2025/08/27/Apple-Store.jpeg"
        },
        {
          "size": "thumb",
          "url": "https://cdn.benzinga.com/files/imagecache/250x187xUP/images/story/2025/08/27/Apple-Store.jpeg"
        }
      ],
      "source": "benzinga",
      "summary": "Apple should be cautious in pursuing mega-deals in AI, as history shows that they often end in regret.",
      "symbols": [
        "AAPL",
        "GOOGL",
        "META",
        "MSFT",
        "NFLX",
        "T",
        "TSLA"
      ],
      "updated_at": "2025-08-27T16:59:50Z",
      "url": "https://www.benzinga.com/markets/tech/25/08/47365037/apple-hunts-big-ai-deals-but-time-warner-nokia-still-haunt-the-ma-playbook"
    }
  ],
  "next_page_token": "MTc1NjMxMzk5MDAwMDAwMDAwMHw0NzM2NTAzNw=="
}